ssvlogger/common.py
ssvlogger/logger.py
ssvlogger/matches/__init__.py
ssvlogger/matches/consensus.py
ssvlogger/matches/controller.py
ssvlogger/matches/controller_commitee.py
ssvlogger/matches/controller_validator.py
ssvlogger/matches/duty_scheduler.py
ssvlogger/matches/event_handler.py
ssvlogger/matches/event_syncer.py
ssvlogger/matches/execution_client.py
ssvlogger/matches/p2pnetwork.py
ssvlogger/matches/p2pnetwork_conn_handler.py
ssvlogger-1.7.1.dist-info/licenses/LICENSE
ssvlogger-1.7.1.dist-info/METADATA
ssvlogger-1.7.1.dist-info/WHEEL
ssvlogger-1.7.1.dist-info/entry_points.txt
ssvlogger-1.7.1.dist-info/top_level.txt
ssvlogger-1.7.1.dist-info/RECORD
