Metadata-Version: 2.4
Name: ssvlogger
Version: 1.7.1
Summary: A simple python package to parse SSV node logs and make them legible
Author: SirSpudlington
License:                                  Apache License
Project-URL: Homepage, https://github.com/SirSpudlington/ssvlogger
Project-URL: Issues, https://github.com/SirSpudlington/ssvlogger/issues
Keywords: SSV,logging
Classifier: Programming Language :: Python :: 3
Classifier: License :: OSI Approved :: Apache Software License
Classifier: Operating System :: OS Independent
Requires-Python: >=3.11
License-File: LICENSE
Requires-Dist: colorama>=0.4.6
Dynamic: license-file
